topsis_baneet_102203180/__init__.py
topsis_baneet_102203180/topsis.py
Topsis_BaneetSingh_102203180-1.0.0.dist-info/LICENSE.txt
Topsis_BaneetSingh_102203180-1.0.0.dist-info/METADATA
Topsis_BaneetSingh_102203180-1.0.0.dist-info/WHEEL
Topsis_BaneetSingh_102203180-1.0.0.dist-info/entry_points.txt
Topsis_BaneetSingh_102203180-1.0.0.dist-info/top_level.txt
Topsis_BaneetSingh_102203180-1.0.0.dist-info/RECORD
