Metadata-Version: 2.2
Name: Topsis-BaneetSingh-102203180
Version: 1.0.0
Summary: A TOPSIS implementation for multiple-criteria decision analysis
Home-page: https://github.com/Baneet2s/topsis
Author: Baneet Singh
Author-email: 2baneetsingh@gmail.com
Classifier: Programming Language :: Python :: 3
Classifier: License :: OSI Approved :: MIT License
Classifier: Operating System :: OS Independent
Requires-Python: >=3.6
License-File: LICENSE.txt
Requires-Dist: numpy
Requires-Dist: pandas
Dynamic: author
Dynamic: author-email
Dynamic: classifier
Dynamic: description
Dynamic: description-content-type
Dynamic: home-page
Dynamic: requires-dist
Dynamic: requires-python
Dynamic: summary
